bhavcopy/__init__.py
bhavcopy/downloader.py
bhavcopy-2.0.dist-info/LICENCE.txt
bhavcopy-2.0.dist-info/METADATA
bhavcopy-2.0.dist-info/WHEEL
bhavcopy-2.0.dist-info/top_level.txt
bhavcopy-2.0.dist-info/RECORD
