Metadata-Version: 2.1
Name: bhavcopy
Version: 2.0
Summary: Download NSE Bhavcopy Data
Home-page: 
Author: Ajay
Author-email: ajaydpawar@gmail.com
License: MIT
Keywords: Bhavcopy
Classifier: Development Status :: 5 - Production/Stable
Classifier: Intended Audience :: Education
Classifier: Operating System :: Microsoft :: Windows :: Windows 10
Classifier: License :: OSI Approved :: MIT License
Classifier: Programming Language :: Python :: 3
License-File: LICENCE.txt
Requires-Dist: pandas
Requires-Dist: numpy
Requires-Dist: requests
